dtp/__init__.py
dtp/core.py
dtp/decoy_template.json
dtp/templates/finance_template.json
dtp/templates/gaming_template.json
dtp/templates/healthcare_template.json
dtp_security-1.0.0.dist-info/licenses/LICENSE
dtp_security-1.0.0.dist-info/METADATA
dtp_security-1.0.0.dist-info/WHEEL
dtp_security-1.0.0.dist-info/top_level.txt
dtp_security-1.0.0.dist-info/RECORD
