Metadata-Version: 2.4
Name: dtp-security
Version: 1.0.0
Summary: Advanced cryptographic SDK with steganography and active defense capabilities
Home-page: https://github.com/vinothvbt/DTP-password-manager
Author: Jeyashree Narayanan
Author-email: Jeyashree Narayanan <jeyashree.narayanan@example.com>
License: Apache-2.0
Project-URL: Homepage, https://github.com/vinothvbt/DTP-password-manager
Project-URL: Documentation, https://github.com/vinothvbt/DTP-password-manager#readme
Project-URL: Repository, https://github.com/vinothvbt/DTP-password-manager
Project-URL: Bug Reports, https://github.com/vinothvbt/DTP-password-manager/issues
Keywords: security,cryptography,steganography,decoy,active-defense,cybersecurity,encryption
Classifier: Development Status :: 5 - Production/Stable
Classifier: Intended Audience :: Developers
Classifier: Intended Audience :: Information Technology
Classifier: Topic :: Software Development :: Libraries :: Python Modules
Classifier: Topic :: Security :: Cryptography
Classifier: Topic :: Security
Classifier: License :: OSI Approved :: Apache Software License
Classifier: Programming Language :: Python :: 3
Classifier: Programming Language :: Python :: 3.8
Classifier: Programming Language :: Python :: 3.9
Classifier: Programming Language :: Python :: 3.10
Classifier: Programming Language :: Python :: 3.11
Classifier: Programming Language :: Python :: 3.12
Classifier: Operating System :: OS Independent
Requires-Python: >=3.8
License-File: LICENSE
Requires-Dist: pycryptodome>=3.15.0
Provides-Extra: dev
Requires-Dist: pytest>=6.0; extra == "dev"
Requires-Dist: pytest-cov>=2.0; extra == "dev"
Requires-Dist: black>=22.0; extra == "dev"
Requires-Dist: flake8>=4.0; extra == "dev"
Provides-Extra: demo
Requires-Dist: flask>=2.0.0; extra == "demo"
Dynamic: author
Dynamic: home-page
Dynamic: license-file
Dynamic: requires-python
